Changelog
LICENSE
MANIFEST.in
README.rst
requirements.txt
setup.py
pyserve/__init__.py
pyserve/app.py
pyserve/bottle.py
pyserve/core.py
pyserve/icons.py
pyserve/main.py
pyserve.egg-info/PKG-INFO
pyserve.egg-info/SOURCES.txt
pyserve.egg-info/dependency_links.txt
pyserve.egg-info/entry_points.txt
pyserve.egg-info/requires.txt
pyserve.egg-info/top_level.txt
pyserve/static/_pyserve_.html
pyserve/static/asc.gif
pyserve/static/desc.gif
pyserve/static/serve.css
pyserve/static/icons/application.png
pyserve/static/icons/application_osx.png
pyserve/static/icons/application_osx_terminal.png
pyserve/static/icons/application_xp_terminal.png
pyserve/static/icons/cd.png
pyserve/static/icons/cog.png
pyserve/static/icons/comment.png
pyserve/static/icons/cross.png
pyserve/static/icons/cup.png
pyserve/static/icons/cursor.png
pyserve/static/icons/database.png
pyserve/static/icons/disk.png
pyserve/static/icons/error.png
pyserve/static/icons/feed.png
pyserve/static/icons/file.png
pyserve/static/icons/film.png
pyserve/static/icons/folder.png
pyserve/static/icons/font.png
pyserve/static/icons/key.png
pyserve/static/icons/layout.png
pyserve/static/icons/music.png
pyserve/static/icons/package.png
pyserve/static/icons/page_code.png
pyserve/static/icons/page_white_acrobat.png
pyserve/static/icons/page_white_actionscript.png
pyserve/static/icons/page_white_c.png
pyserve/static/icons/page_white_code.png
pyserve/static/icons/page_white_code_red.png
pyserve/static/icons/page_white_cplusplus.png
pyserve/static/icons/page_white_cup.png
pyserve/static/icons/page_white_database.png
pyserve/static/icons/page_white_excel.png
pyserve/static/icons/page_white_flash.png
pyserve/static/icons/page_white_gear.png
pyserve/static/icons/page_white_h.png
pyserve/static/icons/page_white_php.png
pyserve/static/icons/page_white_powerpoint.png
pyserve/static/icons/page_white_ruby.png
pyserve/static/icons/page_white_text.png
pyserve/static/icons/page_white_text_width.png
pyserve/static/icons/page_white_visualstudio.png
pyserve/static/icons/page_white_word.png
pyserve/static/icons/page_white_zip.png
pyserve/static/icons/parent.png
pyserve/static/icons/picture.png
pyserve/static/icons/pictures.png
