Metadata-Version: 1.0
Name: pyserve
Version: 0.2.7
Summary: Serve local dirs.
Home-page: http://github.com/klen/pyserve
Author: Kirill Klenov <horneds@gmail.com>
Author-email: horneds@gmail.com
License: GNU LGPL
Platform: UNKNOWN
Classifier: Development Status :: 4 - Beta
Classifier: Intended Audience :: Developers
Classifier: Intended Audience :: System Administrators
Classifier: Natural Language :: Russian
Classifier: Natural Language :: English
Classifier: License :: OSI Approved :: GNU Library or Lesser General Public License (LGPL)
Classifier: Programming Language :: Python
Classifier: Environment :: Console
Classifier: Topic :: Software Development :: Code Generators
